flask_watchlog_apm/__init__.py
flask_watchlog_apm/collector.py
flask_watchlog_apm/error_handler.py
flask_watchlog_apm/middleware.py
flask_watchlog_apm/patch_flask_routes.py
flask_watchlog_apm/sender.py
flask_watchlog_apm-0.1.6.dist-info/licenses/LICENSE
flask_watchlog_apm-0.1.6.dist-info/METADATA
flask_watchlog_apm-0.1.6.dist-info/WHEEL
flask_watchlog_apm-0.1.6.dist-info/top_level.txt
flask_watchlog_apm-0.1.6.dist-info/RECORD
