Metadata-Version: 2.4
Name: flask_watchlog_apm
Version: 0.1.6
Summary: Lightweight APM for Flask that sends metrics to Watchlog Agent
Home-page: https://github.com/watchlogserver/flask_watchlog_apm
Author: Mohammadreza
Author-email: mohammadnajm75@gmail.com
Classifier: Programming Language :: Python :: 3
Classifier: Framework :: Flask
Classifier: License :: OSI Approved :: MIT License
Classifier: Operating System :: OS Independent
Requires-Python: >=3.6
License-File: LICENSE
Requires-Dist: Flask
Requires-Dist: psutil
Requires-Dist: requests
Dynamic: author
Dynamic: author-email
Dynamic: classifier
Dynamic: description
Dynamic: description-content-type
Dynamic: home-page
Dynamic: license-file
Dynamic: requires-dist
Dynamic: requires-python
Dynamic: summary
